Workbook
Name Aporte: Hoja1!$C$17
Name patrimonio: Hoja1!$C$20
Name quantidade_anos: Hoja1!$C$18
Name rendimento_carteira: Hoja1!$C$13
Name salario: Hoja1!$C$12
Name sugestao_investimento: Hoja1!$C$14
Name taxa_mensal: Hoja1!$C$19

Sheet Hoja1
B11: Configurações
B12: Salario | C12: 4200
B13: Rendimento carteira | C13: 0.0089
B14: Sugestão de investimento (30%) | C14: =C12*0.3 -> 1260
B16: Investimento mensal
B17: Quanto investir por mês? | C17: 1260
B18: Por quantos anos? | C18: 10
B19: Taxa de rendimento mensal? | C19: 0.01079
B20: Patrimônio acumulado? | C20: =FV(taxa_mensal,quantidade_anos*12,Aporte*-1) -> 306538.11
B21: Dividendos mensais? | C21: =C20*C19 -> 3307.5462
B23: Cénarios Dividendo
A24: 2 | B24: Quanto em 2 anos? | C24: =FV($C$19,A$24*12,$C$17*-1) -> 34306.81 | D24: =C24*rendimento_carteira -> 305.33061
A25: 5 | B25: Quanto em 5 anos? | C25: =FV($C$19,A$25*12,$C$17*-1) -> 105558.91 | D25: =C25*rendimento_carteira -> 939.47431
A26: 10 | B26: Quanto em 10 anos? | C26: =FV($C$19,A26*12,$C$17*-1) -> 306538.11 | D26: =C26*rendimento_carteira -> 2728.1892
A27: 20 | B27: Quanto em 20 anos? | C27: =FV($C$19,A27*12,$C$17*-1) -> 1417750 | D27: =C27*rendimento_carteira -> 12617.975
A28: 30 | B28: Quanto em 30 anos? | C28: =FV($C$19,A28*12,$C$17*-1) -> 5445933.8 | D28: =C28*rendimento_carteira -> 48468.811
B31: Perfil | C31: CONSERVADOR
B32: VALOR A SER INVESTIDO POR MÊS | C32: =Aporte -> 1260
B34: TIPO DE FII | C34: PORCENTUAL SUGERIDO | D34: VALORES
B35: PAPEL | C35: =VLOOKUP($C$31&"-"&B35,Hoja2!A1:D21,4,FALSE) -> 0.3 | D35: =C35*$C$32 -> 378
B36: TIJOLO | C36: =VLOOKUP($C$31&"-"&B36,Hoja2!A2:D22,4,FALSE) -> 0.5 | D36: =C36*$C$32 -> 630
B37: HIBRIDOS | C37: =VLOOKUP($C$31&"-"&B37,Hoja2!A3:D23,4,FALSE) -> 0.1 | D37: =C37*$C$32 -> 126
B38: FOFS | C38: =VLOOKUP($C$31&"-"&B38,Hoja2!A4:D24,4,FALSE) -> 0.1 | D38: =C38*$C$32 -> 126
B39: DESENVOLVIMENTO | C39: =VLOOKUP($C$31&"-"&B39,Hoja2!A5:D25,4,FALSE) -> 0 | D39: =C39*$C$32 -> 0
B40: HOTELARIAS | C40: =VLOOKUP($C$31&"-"&B40,Hoja2!A6:D26,4,FALSE) -> 0 | D40: =C40*$C$32 -> 0

Sheet Hoja2
A3: CHAVE | B3: PERFIL | C3: TIPO DE FII | D3: PORCENTUAL
A4: =B4&"-"&C4 -> CONSERVADOR-PAPEL | B4: CONSERVADOR | C4: PAPEL | D4: 0.3 | I4: %
A5: =B5&"-"&C5 -> CONSERVADOR-TIJOLO | B5: CONSERVADOR | C5: TIJOLO | D5: 0.5 | G5: MODERADO-TIJOLO | I5: =VLOOKUP(G5,$A:$D,4,FALSE) -> 0.4
A6: =B6&"-"&C6 -> CONSERVADOR-HIBRIDOS | B6: CONSERVADOR | C6: HIBRIDOS | D6: 0.1
A7: =B7&"-"&C7 -> CONSERVADOR-FOFS | B7: CONSERVADOR | C7: FOFS | D7: 0.1
A8: =B8&"-"&C8 -> CONSERVADOR-DESENVOLVIMENTO | B8: CONSERVADOR | C8: DESENVOLVIMENTO | D8: 0
A9: =B9&"-"&C9 -> CONSERVADOR-HOTELARIAS | B9: CONSERVADOR | C9: HOTELARIAS | D9: 0
A10: =B10&"-G14"&C10 -> MODERADO-G14PAPEL | B10: MODERADO | C10: PAPEL | D10: 0.32
A11: =B11&"-"&C11 -> MODERADO-TIJOLO | B11: MODERADO | C11: TIJOLO | D11: 0.4
A12: =B12&"-"&C12 -> MODERADO-HIBRIDOS | B12: MODERADO | C12: HIBRIDOS | D12: 0.08
A13: =B13&"-"&C13 -> MODERADO-FOFS | B13: MODERADO | C13: FOFS | D13: 0.1
A14: =B14&"-"&C14 -> MODERADO-DESENVOLVIMENTO | B14: MODERADO | C14: DESENVOLVIMENTO | D14: 0.1
A15: =B15&"-"&C15 -> MODERADO-HOTELARIAS | B15: MODERADO | C15: HOTELARIAS | D15: 0.1
A16: =B16&"-"&C16 -> AGRESSIVO-PAPEL | B16: AGRESSIVO | C16: PAPEL | D16: 0.5
A17: =B17&"-"&C17 -> AGRESSIVO-TIJOLO | B17: AGRESSIVO | C17: TIJOLO | D17: 0.1
A18: =B18&"-"&C18 -> AGRESSIVO-HIBRIDOS | B18: AGRESSIVO | C18: HIBRIDOS | D18: 0.05
A19: =B19&"-"&C19 -> AGRESSIVO-FOFS | B19: AGRESSIVO | C19: FOFS | D19: 0.05
A20: =B20&"-"&C20 -> AGRESSIVO-DESENVOLVIMENTO | B20: AGRESSIVO | C20: DESENVOLVIMENTO | D20: 0.2
A21: =B21&"-"&C21 -> AGRESSIVO-HOTELARIAS | B21: AGRESSIVO | C21: HOTELARIAS | D21: 0.1

Sheet Hoja3
